ecs/__init__.py
ecs/ecs.py
ecs/exceptions.py
ecs/extra_filters.py
ecs/helper.py
ecs/init.py
ecs/project_loader.py
ecs/render.py
ecs/bin/__init__.py
ecs/bin/ecsctl.py
ecscontrol-1.0.1.dist-info/LICENSE.txt
ecscontrol-1.0.1.dist-info/METADATA
ecscontrol-1.0.1.dist-info/WHEEL
ecscontrol-1.0.1.dist-info/entry_points.txt
ecscontrol-1.0.1.dist-info/top_level.txt
ecscontrol-1.0.1.dist-info/RECORD
