Metadata-Version: 2.1
Name: ecscontrol
Version: 1.0.1
Summary: Tool for automation of deployments to AWS ECS
Home-page: https://github.com/lejmr/ecsctl
Author: Milos Kozak
Author-email: milos.kozak@lejmr.com
License: MIT
Download-URL: https://github.com/lejmr/ecsctl/archive/v_01.tar.gz
Platform: UNKNOWN
Classifier: Development Status :: 3 - Alpha
Classifier: Intended Audience :: Developers
Classifier: Topic :: Software Development :: Build Tools
Classifier: License :: OSI Approved :: MIT License
Classifier: Programming Language :: Python :: 3
Classifier: Programming Language :: Python :: 3.4
Classifier: Programming Language :: Python :: 3.5
Classifier: Programming Language :: Python :: 3.6
License-File: LICENSE.txt
Requires-Dist: Click
Requires-Dist: Jinja2
Requires-Dist: python-magic
Requires-Dist: python-slugify
Requires-Dist: dateparser
Requires-Dist: boto3
Requires-Dist: PyYAML
